leb128.cp37-win_amd64.pyd
cyleb128-0.1.3.dist-info/LICENSE
cyleb128-0.1.3.dist-info/METADATA
cyleb128-0.1.3.dist-info/WHEEL
cyleb128-0.1.3.dist-info/top_level.txt
cyleb128-0.1.3.dist-info/RECORD
